asyncio_multilock/__init__.py
asyncio_multilock/py.typed
asyncio_multilock-0.2.0.dist-info/METADATA
asyncio_multilock-0.2.0.dist-info/WHEEL
asyncio_multilock-0.2.0.dist-info/RECORD
