Metadata-Version: 2.3
Name: asyncio-multilock
Version: 0.2.0
Summary: asyncio shared/exclusive mode lock
Author-email: Connor Newton <connor@ifthenelse.io>
Requires-Python: <4.0,>=3.9
